iam_cli/__init__.py
iam_cli/command.py
iam_cli/create_yaml.py
iam_cli/deploy_cfn.py
iam_cli/main.py
iam_cli/tools.py
iam_cli/validators.py
aws_iam_cli-1.2.0.dist-info/LICENSE
aws_iam_cli-1.2.0.dist-info/METADATA
aws_iam_cli-1.2.0.dist-info/WHEEL
aws_iam_cli-1.2.0.dist-info/entry_points.txt
aws_iam_cli-1.2.0.dist-info/top_level.txt
aws_iam_cli-1.2.0.dist-info/RECORD
